cli/__init__.py
cli/dsl_format.py
cli/main.py
cli/mcp.py
cli/promptware_old.py
cli/toolgen.py
cli/formatters/__init__.py
cli/formatters/promptware_dsl_formatter.py
daemon/__init__.py
daemon/deps_utils.py
daemon/gateway.py
daemon/mcpd.py
daemon/uds_shim.py
docs/AI_AGENT_GUIDE.md
docs/ARCHITECTURE.md
docs/BLOCK_PARSING_IMPLEMENTATION_CHECKLIST.md
docs/BLOCK_PARSING_IMPLEMENTATION_EXAMPLE.md
docs/BLOCK_PARSING_RESEARCH.md
docs/CREATE_DEMO_GIF.md
docs/DEVELOPMENT.md
docs/DOTNET_GENERATOR_V2.md
docs/DOTNET_PARSER_V2.md
docs/EXAMPLES_INDEX.md
docs/GO_GENERATOR_V2.md
docs/GO_PARSER_V2.md
docs/INDEX.md
docs/INTEGRATION_TESTING.md
docs/IR_SPECIFICATION.md
docs/NODEJS_GENERATOR_V2.md
docs/NODEJS_PARSER_V2.md
docs/PRODUCTION_READINESS_PLAN.md
docs/PW_DSL_2.0_SPEC.md
docs/PW_LANGUAGE_GUIDE.md
docs/PW_NATIVE_SYNTAX.md
docs/PYTHON_GENERATOR_V2.md
docs/PYTHON_PARSER_V2.md
docs/QUICK_REFERENCE.md
docs/README.md
docs/RESEARCH_NOTES.md
docs/RUST_GENERATOR_V2.md
docs/RUST_PARSER_V2.md
docs/SAFE_PATTERNS.md
docs/SESSION_SUMMARY.md
docs/TYPE_SYSTEM.md
docs/VS_CODE_EXTENSION.md
docs/WORLD_CLASS_ROADMAP.md
docs/agent-communication-guide.md
docs/agents.md
docs/cheatsheet.md
docs/cli-guide.md
docs/cli-quickstart.md
docs/client-api.md
docs/dependency-management.md
docs/development-guide.md
docs/dual-mode-architecture.md
docs/editor-integration.md
docs/extensability.md
docs/framework-overview.md
docs/installation.md
docs/multi-language-status.md
docs/policy-hooks.md
docs/promptware-dsl-design.md
docs/promptware-dsl-format.md
docs/promptware-dsl-roadmap.md
docs/promptware-dsl-spec.md
docs/promptware-tech.md
docs/roadmap.md
docs/sdk-guide.md
docs/test-batches.md
docs/testing-dotnet-adapter-smoke-tests.md
docs/testing-go-adapter-smoke-tests.md
docs/testing-guide.md
docs/testing-node-adapter-smoke-tests.md
docs/testing-rust-adapter-smoke-tests.md
docs/tool-generator-spec.md
docs/tool-specefications.md
docs/toolgen-cli-usage.md
docs/toolgen-dotnet-adapter-template.md
promptware_dev-2.1.0b11.dist-info/licenses/LICENSE
promptware_dev-2.1.0b11.dist-info/METADATA
promptware_dev-2.1.0b11.dist-info/WHEEL
promptware_dev-2.1.0b11.dist-info/entry_points.txt
promptware_dev-2.1.0b11.dist-info/top_level.txt
promptware_dev-2.1.0b11.dist-info/RECORD
